python_purify/__init__.py
python_purify/core.py
python_purify/exceptions.py
python_purify/tests.py
python_purify-2.0.1.dist-info/LICENSE.txt
python_purify-2.0.1.dist-info/METADATA
python_purify-2.0.1.dist-info/WHEEL
python_purify-2.0.1.dist-info/top_level.txt
python_purify-2.0.1.dist-info/RECORD
