Metadata-Version: 2.1
Name: python-purify
Version: 2.0.1
Summary: A python API for Web Purify
Home-page: https://github.com/kingthomasc/python-purify
Author: Tom King, Kory Donati
Author-email: tomk@bixly.com, korydonati@gmail.com
License: UNKNOWN
Download-URL: https://github.com/kingthomasc/python-purify/tarball/2.0.1
Keywords: profanity,filter,web purify,webpurify
Platform: UNKNOWN
Classifier: Programming Language :: Python :: 2
Classifier: Programming Language :: Python :: 3
Classifier: License :: OSI Approved :: MIT License
Classifier: Operating System :: OS Independent
Requires-Dist: six
